[{"category":"Canada","position":0,"value":865},{"category":"Australie","position":0,"value":767},{"category":"États-Unis","position":0,"value":594},{"category":"Danemark","position":0,"value":295},{"category":"Norvège","position":0,"value":246},{"category":"Japon","position":0,"value":177},{"category":"Nouvelle-Zélande","position":0,"value":169},{"category":"Pays-Bas","position":0,"value":42},{"category":"Allemagne","position":0,"value":22},{"category":"République de Corée","position":0,"value":16}]