[{"category":"Allemagne","position":0,"value":10657},{"category":"Royaume-Uni","position":0,"value":5000},{"category":"Belgique","position":0,"value":4618},{"category":"Suisse","position":0,"value":3258},{"category":"Pays-Bas","position":0,"value":3149},{"category":"États-Unis","position":0,"value":1684},{"category":"Portugal","position":0,"value":1664},{"category":"Italie","position":0,"value":1514},{"category":"Japon","position":0,"value":1007},{"category":"Mexique","position":0,"value":969}]