[{"category":"Allemagne","position":0,"value":70388},{"category":"Suisse","position":0,"value":17822},{"category":"Royaume-Uni","position":0,"value":17000},{"category":"Espagne","position":0,"value":14955},{"category":"Belgique","position":0,"value":6313},{"category":"Pays-Bas","position":0,"value":5147},{"category":"Autriche","position":0,"value":4101},{"category":"États-Unis","position":0,"value":3298},{"category":"Japon","position":0,"value":2430},{"category":"Luxembourg","position":0,"value":1649}]