[{"category":"Japon","position":0,"value":21895},{"category":"États-Unis","position":0,"value":12382},{"category":"Canada","position":0,"value":7117},{"category":"Nouvelle-Zélande","position":0,"value":3233},{"category":"Allemagne","position":0,"value":3077},{"category":"Royaume-Uni","position":0,"value":3000},{"category":"Australie","position":0,"value":2300},{"category":"Pologne","position":0,"value":342},{"category":"Pays-Bas","position":0,"value":325},{"category":"Italie","position":0,"value":281}]