[{"category":"Royaume-Uni","position":0,"value":7000},{"category":"Australie","position":0,"value":5396},{"category":"Japon","position":0,"value":2320},{"category":"États-Unis","position":0,"value":2014},{"category":"Nouvelle-Zélande","position":0,"value":1238},{"category":"Allemagne","position":0,"value":696},{"category":"Canada","position":0,"value":640},{"category":"République de Corée","position":0,"value":432},{"category":"Pays-Bas","position":0,"value":216},{"category":"France","position":0,"value":103}]