[{"category":"Allemagne","position":0,"value":16425},{"category":"États-Unis","position":0,"value":13188},{"category":"Espagne","position":0,"value":8041},{"category":"Japon","position":0,"value":5024},{"category":"Tchéquie","position":0,"value":4675},{"category":"République de Corée","position":0,"value":3742},{"category":"France","position":0,"value":3189},{"category":"Canada","position":0,"value":3117},{"category":"Italie","position":0,"value":2880},{"category":"Autriche","position":0,"value":2463}]